liquibase_checks_python/__init__.py
liquibase_checks_python/liquibase_changesets.py
liquibase_checks_python/liquibase_constants.py
liquibase_checks_python/liquibase_database.py
liquibase_checks_python/liquibase_exception.py
liquibase_checks_python/liquibase_json.py
liquibase_checks_python/liquibase_utilities.py
liquibase_checks_python-2.0.0.dist-info/LICENSE.txt
liquibase_checks_python-2.0.0.dist-info/METADATA
liquibase_checks_python-2.0.0.dist-info/WHEEL
liquibase_checks_python-2.0.0.dist-info/top_level.txt
liquibase_checks_python-2.0.0.dist-info/RECORD
