Metadata-Version: 2.2
Name: liquibase-checks-python
Version: 2.0.0
Summary: Use python to write your custom policy checks for Liquibase
Author-email: Liquibase Team <support@liquibase.com>
Project-URL: Homepage, https://www.liquibase.com/
Project-URL: Issues, https://www.liquibase.com/support
Classifier: Programming Language :: Python :: 3
Classifier: Operating System :: OS Independent
Classifier: Topic :: Database
Requires-Python: >=3.10
License-File: LICENSE.txt
Requires-Dist: simplejson==3.19.2
Requires-Dist: sqlparse==0.5.0
Provides-Extra: dev
Requires-Dist: pytest; extra == "dev"
